Matrixpackage.py
Matrixpackage-1.0.2.dist-info/METADATA
Matrixpackage-1.0.2.dist-info/WHEEL
Matrixpackage-1.0.2.dist-info/top_level.txt
Matrixpackage-1.0.2.dist-info/RECORD
