Metadata-Version: 2.1
Name: Matrixpackage
Version: 1.0.2
Summary: Matrix Package provides matrix addition,subtraction and matrix multiplication
Home-page: https://github.com/pavishri
Author: Pavithra.K, Maria Irudaya Regilan J
Author-email: <pavithrak.vec@gmail.com>
License: UNKNOWN
Platform: UNKNOWN
Classifier: Programming Language :: Python :: 3.5
Classifier: Programming Language :: Python :: 3.6
Classifier: Programming Language :: Python :: 3.7
Classifier: Programming Language :: Python :: 3.8
Classifier: Operating System :: OS Independent
